CPyS/B.py
CPyS/CPS.py
CPyS/VT.py
CPyS/__init__.py
CPyS/plot.py
CPyS/theta.py
CPyS-0.0.6.dist-info/LICENSE
CPyS-0.0.6.dist-info/METADATA
CPyS-0.0.6.dist-info/WHEEL
CPyS-0.0.6.dist-info/top_level.txt
CPyS-0.0.6.dist-info/RECORD
