Metadata-Version: 2.1
Name: CPyS
Version: 0.0.6
Summary: A python package from compute the Hart Cyclone Phase Space parameters
Author: Stella Bourdin
Author-email: stella.bourdin@lsce.ipsl.fr
Classifier: Development Status :: 3 - Alpha
Classifier: Programming Language :: Python :: 3
Classifier: License :: OSI Approved :: GNU General Public License v3 (GPLv3)
Classifier: Operating System :: OS Independent
Requires-Python: >=3.6
License-File: LICENSE
Requires-Dist: numpy
Requires-Dist: pandas
Requires-Dist: xarray
Requires-Dist: pyproj
Requires-Dist: matplotlib
